{
  "actions": {
    "createBatch": {
      "href": "/o/headless-batch-engine/v1.0/import-task/com.liferay.headless.admin.list.type.dto.v1_0.ListTypeDefinition",
      "method": "POST"
    },
    "deleteBatch": {
      "href": "/o/headless-batch-engine/v1.0/import-task/com.liferay.headless.admin.list.type.dto.v1_0.ListTypeDefinition",
      "method": "DELETE"
    },
    "updateBatch": {
      "href": "/o/headless-batch-engine/v1.0/import-task/com.liferay.headless.admin.list.type.dto.v1_0.ListTypeDefinition",
      "method": "PUT"
    }
  },
  "configuration": {
    "callbackURL": null,
    "className": "com.liferay.headless.admin.list.type.dto.v1_0.ListTypeDefinition",
    "companyId": 38896022093338,
    "multiCompany": false,
    "parameters": {
      "className": "com.liferay.headless.admin.list.type.dto.v1_0.ListTypeDefinition",
      "contentType": "jsont",
      "createStrategy": "INSERT",
      "importStrategy": "ON_ERROR_FAIL",
      "updateStrategy": "UPDATE"
    },
    "taskItemDelegateName": "",
    "userId": 20122,
    "version": "v1.0"
  },
  "items": [
    {
      "actions": {
        "get": {
          "href": "/headless-batch-engine/v1.0/list-type-definitions/50549",
          "method": "GET"
        },
        "permissions": {
          "href": "/headless-batch-engine/v1.0/list-type-definitions/50549",
          "method": "PATCH"
        },
        "update": {
          "href": "/headless-batch-engine/v1.0/list-type-definitions/50549",
          "method": "PUT"
        }
      },
      "dateCreated": "2024-07-24T10:23:00Z",
      "dateModified": "2024-07-24T10:24:33Z",
      "externalReferenceCode": "d544f547-ecd3-0996-f829-90b49306c88e",
      "id": 50549,
      "listTypeEntries": [
        {
          "dateCreated": "2024-07-24T10:23:48Z",
          "dateModified": "2024-07-24T10:24:33Z",
          "externalReferenceCode": "7838fdea-e6a8-f445-20d0-6adb63f61d28",
          "id": 50550,
          "key": "cndnusd",
          "name": "USD",
          "name_i18n": {
            "en-US": "USD"
          },
          "type": ""
        },
        {
          "dateCreated": "2024-07-24T10:24:01Z",
          "dateModified": "2024-07-24T10:24:33Z",
          "externalReferenceCode": "1f7e056a-502c-c391-2f99-80d7673e887b",
          "id": 50551,
          "key": "cndnsgd",
          "name": "SGD",
          "name_i18n": {
            "en-US": "SGD"
          },
          "type": ""
        },
        {
          "dateCreated": "2024-07-24T10:24:21Z",
          "dateModified": "2024-07-24T10:24:33Z",
          "externalReferenceCode": "1eaa2f45-9d6b-a9d5-8cb2-3cd28a88d527",
          "id": 50552,
          "key": "cndninr",
          "name": "INR",
          "name_i18n": {
            "en-US": "INR"
          },
          "type": ""
        }
      ],
      "name": "CNDN Currency",
      "name_i18n": {
        "en-US": "CNDN Currency"
      },
      "system": false
    },
    {
      "actions": {
        "get": {
          "href": "/headless-batch-engine/v1.0/list-type-definitions/50553",
          "method": "GET"
        },
        "permissions": {
          "href": "/headless-batch-engine/v1.0/list-type-definitions/50553",
          "method": "PATCH"
        },
        "update": {
          "href": "/headless-batch-engine/v1.0/list-type-definitions/50553",
          "method": "PUT"
        }
      },
      "dateCreated": "2024-07-24T10:24:43Z",
      "dateModified": "2024-07-24T10:25:59Z",
      "externalReferenceCode": "571d2c9b-43dc-7b9b-7764-6021fdcd7e6d",
      "id": 50553,
      "listTypeEntries": [
        {
          "dateCreated": "2024-07-24T10:24:56Z",
          "dateModified": "2024-07-24T10:25:59Z",
          "externalReferenceCode": "8ed22e1d-1e4f-f112-61b8-deb25f5498f5",
          "id": 50554,
          "key": "sortingCosts",
          "name": "Sorting Costs",
          "name_i18n": {
            "en-US": "Sorting Costs"
          },
          "type": ""
        },
        {
          "dateCreated": "2024-07-24T10:25:03Z",
          "dateModified": "2024-07-24T10:25:59Z",
          "externalReferenceCode": "9aa7224c-8c8b-df22-effb-7007957504de",
          "id": 50555,
          "key": "rebates",
          "name": "Rebates",
          "name_i18n": {
            "en-US": "Rebates"
          },
          "type": ""
        },
        {
          "dateCreated": "2024-07-24T10:25:14Z",
          "dateModified": "2024-07-24T10:25:59Z",
          "externalReferenceCode": "293b6d92-d5f5-69cc-0d48-0f77470dd074",
          "id": 50556,
          "key": "priceProtection",
          "name": "Price Protection",
          "name_i18n": {
            "en-US": "Price Protection"
          },
          "type": ""
        },
        {
          "dateCreated": "2024-07-24T10:25:21Z",
          "dateModified": "2024-07-24T10:25:59Z",
          "externalReferenceCode": "8afa0fa5-aa3e-ff93-7459-7cea0b726c9e",
          "id": 50557,
          "key": "tooling",
          "name": "Tooling",
          "name_i18n": {
            "en-US": "Tooling"
          },
          "type": ""
        },
        {
          "dateCreated": "2024-07-24T10:25:30Z",
          "dateModified": "2024-07-24T10:25:59Z",
          "externalReferenceCode": "a6dbe6b6-50c7-46e1-26d6-d28b8c7f7b17",
          "id": 50558,
          "key": "shippingError",
          "name": "Shipping Error",
          "name_i18n": {
            "en-US": "Shipping Error"
          },
          "type": ""
        },
        {
          "dateCreated": "2024-07-24T10:25:40Z",
          "dateModified": "2024-07-24T10:25:59Z",
          "externalReferenceCode": "899b2a27-f36a-5ae6-0739-453768743eb4",
          "id": 50559,
          "key": "pricingDispute",
          "name": "Pricing Dispute",
          "name_i18n": {
            "en-US": "Pricing Dispute"
          },
          "type": ""
        },
        {
          "dateCreated": "2024-07-24T10:25:48Z",
          "dateModified": "2024-07-24T10:25:59Z",
          "externalReferenceCode": "31730277-d25d-d558-dcc5-09afd3c3a3b9",
          "id": 50560,
          "key": "adminError",
          "name": "Admin Error",
          "name_i18n": {
            "en-US": "Admin Error"
          },
          "type": ""
        },
        {
          "dateCreated": "2024-07-24T10:25:57Z",
          "dateModified": "2024-07-24T10:25:59Z",
          "externalReferenceCode": "ea497730-e58e-72f3-aa86-380e0be6a3a4",
          "id": 50561,
          "key": "others",
          "name": "Others",
          "name_i18n": {
            "en-US": "Others"
          },
          "type": ""
        }
      ],
      "name": "CNDN Reason",
      "name_i18n": {
        "en-US": "CNDN Reason"
      },
      "system": false
    },
    {
      "actions": {
        "get": {
          "href": "/headless-batch-engine/v1.0/list-type-definitions/50562",
          "method": "GET"
        },
        "permissions": {
          "href": "/headless-batch-engine/v1.0/list-type-definitions/50562",
          "method": "PATCH"
        },
        "update": {
          "href": "/headless-batch-engine/v1.0/list-type-definitions/50562",
          "method": "PUT"
        }
      },
      "dateCreated": "2024-07-24T10:26:12Z",
      "dateModified": "2024-07-24T10:26:53Z",
      "externalReferenceCode": "520e6f07-81ab-e4d4-6e13-bfddf978bd56",
      "id": 50562,
      "listTypeEntries": [
        {
          "dateCreated": "2024-07-24T10:26:35Z",
          "dateModified": "2024-07-24T10:26:53Z",
          "externalReferenceCode": "545b01da-3ebd-56bf-4754-0dbb77e70885",
          "id": 50563,
          "key": "cndncsadept",
          "name": "CSA",
          "name_i18n": {
            "en-US": "CSA"
          },
          "type": ""
        },
        {
          "dateCreated": "2024-07-24T10:26:51Z",
          "dateModified": "2024-07-24T10:26:53Z",
          "externalReferenceCode": "db6a4b5e-dd82-8065-7332-06e737b750ae",
          "id": 50564,
          "key": "cndnisdept",
          "name": "IS",
          "name_i18n": {
            "en-US": "IS"
          },
          "type": ""
        }
      ],
      "name": "CNDN Department",
      "name_i18n": {
        "en-US": "CNDN Department"
      },
      "system": false
    },
    {
      "actions": {
        "delete": {
          "href": "/headless-batch-engine/v1.0/list-type-definitions/51138",
          "method": "DELETE"
        },
        "get": {
          "href": "/headless-batch-engine/v1.0/list-type-definitions/51138",
          "method": "GET"
        },
        "permissions": {
          "href": "/headless-batch-engine/v1.0/list-type-definitions/51138",
          "method": "PATCH"
        },
        "update": {
          "href": "/headless-batch-engine/v1.0/list-type-definitions/51138",
          "method": "PUT"
        }
      },
      "dateCreated": "2024-07-25T07:08:53Z",
      "dateModified": "2024-07-25T07:09:27Z",
      "externalReferenceCode": "fd6a3cfa-e1ec-e60a-88ac-e4492f063434",
      "id": 51138,
      "listTypeEntries": [
        {
          "dateCreated": "2024-07-25T07:09:10Z",
          "dateModified": "2024-07-25T07:09:27Z",
          "externalReferenceCode": "d12a4978-d1c9-a076-24d4-3b55fe8a2c75",
          "id": 51139,
          "key": "cndncredit",
          "name": "Credit",
          "name_i18n": {
            "en-US": "Credit"
          },
          "type": ""
        },
        {
          "dateCreated": "2024-07-25T07:09:22Z",
          "dateModified": "2024-07-25T07:09:27Z",
          "externalReferenceCode": "aeb14ff7-769f-62cc-ebe1-1eae3c397453",
          "id": 51140,
          "key": "cndndebit",
          "name": "Debit",
          "name_i18n": {
            "en-US": "Debit"
          },
          "type": ""
        }
      ],
      "name": "CNDN Voucher",
      "name_i18n": {
        "en-US": "CNDN Voucher"
      },
      "system": false
    }
  ]
}